aext_panels_server/__init__.py
aext_panels_server-0.0.1.dist-info/METADATA
aext_panels_server-0.0.1.dist-info/WHEEL
aext_panels_server-0.0.1.dist-info/RECORD
