Metadata-Version: 2.1
Name: aext-panels-server
Version: 0.0.1
Summary: The aext-panels-server component of anaconda-toolbox
License-Expression: BSD-3-Clause
